ipsumheroes/CHANGELOG.md
ipsumheroes/__init__.py
ipsumheroes/__main__.py
ipsumheroes/core.py
ipsumheroes/generator.py
ipsumheroes/py.typed
ipsumheroes/resources/__init__.py
ipsumheroes/resources/config_schema.py
ipsumheroes/resources/help.py
ipsumheroes/resources/topic_data.py
ipsumheroes/topic.py
ipsumheroes-0.1.0.dist-info/licenses/LICENSE
ipsumheroes-0.1.0.dist-info/WHEEL
ipsumheroes-0.1.0.dist-info/METADATA
ipsumheroes-0.1.0.dist-info/RECORD
