Metadata-Version: 2.4
Name: ipsumheroes
Version: 0.1.0
Summary: A lorem ipsum generator inspired by history’s luminaries and heroes.
Keywords: loremipsum,lorem,ipsum,heroes,luminaries,placeholder,text-generator
Author: Rik Roos, Roos IT Logics
Author-email: Rik Roos, Roos IT Logics <opensource@bytelogic.nl>
License-Expression: MIT
License-File: LICENSE
Classifier: Programming Language :: Python :: 3
Classifier: License :: OSI Approved :: MIT License
Classifier: Operating System :: OS Independent
Classifier: Topic :: Text Processing
Classifier: Topic :: Software Development :: Libraries
Requires-Dist: konvigius>=0.0.4
Requires-Python: >=3.10
Project-URL: Changelog, https://github.com/RikRoos/ipsumheroes/blob/master/src/ipsumheroes/CHANGELOG.md
Project-URL: Documentation, https://github.com/RikRoos/ipsumheroes/blob/master/MANUAL.md
Project-URL: Homepage, https://github.com/RikRoos/ipsumheroes
Project-URL: Issues, https://github.com/RikRoos/ipsumheroes/issues
Project-URL: Source, https://github.com/RikRoos/ipsumheroes/tree/master/src/ipsumheroes
